dirct/__init__.py
dirct/_base_dirct.py
dirct/_self_dirct.py
dirct/_sub_dict.py
dirct/dirct.py
dirct/exceptions.py
dirct/key_mappers/__init__.py
dirct/key_mappers/basename_key_mapper.py
dirct/key_mappers/exact_key_mapper.py
dirct/key_mappers/key_mapper.py
dirct/loaders.py
dirct/py.typed
dirct-2.0.1.dist-info/LICENSE
dirct-2.0.1.dist-info/METADATA
dirct-2.0.1.dist-info/WHEEL
dirct-2.0.1.dist-info/RECORD
