Metadata-Version: 2.1
Name: dirct
Version: 2.0.1
Summary: A dict that reflects the contents of a directory.
Home-page: https://github.com/abrahammurciano/python-dirct
License: GPLv3
Author: Abraham Murciano
Author-email: abrahammurciano@gmail.com
Requires-Python: >=3.11
Classifier: License :: Other/Proprietary License
Classifier: Programming Language :: Python :: 3
Classifier: Programming Language :: Python :: 3.11
Classifier: Programming Language :: Python :: 3.12
Requires-Dist: more-itertools (>=10.1.0)
Requires-Dist: pyyaml (>=6.0.1)
Project-URL: Documentation, https://abrahammurciano.github.io/python-dirct/dirct
Project-URL: Repository, https://github.com/abrahammurciano/python-dirct
